vinted/__init__.py
vinted/auth.py
vinted/client.py
vinted/constants.py
vinted/exceptions.py
vinted/session.py
vinted/utils.py
vinted/api/__init__.py
vinted/api/base.py
vinted/api/catalog.py
vinted/api/items.py
vinted/models/__init__.py
vinted/models/config.py
vinted/models/item.py
vinted/storage/__init__.py
vinted/storage/base.py
vinted/storage/json.py
vinted/storage/mozilla.py
vinted/storage/pickle.py
vinted_api_kit-1.0.0.dist-info/METADATA
vinted_api_kit-1.0.0.dist-info/WHEEL
vinted_api_kit-1.0.0.dist-info/licenses/LICENSE
vinted_api_kit-1.0.0.dist-info/RECORD
