Metadata-Version: 2.4
Name: vinted-api-kit
Version: 1.0.0
Summary: Lightweight asynchronous Python client library for accessing Vinted API and scraping item data.
Project-URL: Homepage, https://github.com/vlymar1/vinted-api-kit
Project-URL: Documentation, https://github.com/vlymar1/vinted-api-kit
Project-URL: Repository, https://github.com/vlymar1/vinted-api-kit
Author-email: Lymar Volodymyr <volodymyr.lymar1@gmail.com>
Maintainer-email: Lymar Volodymyr <volodymyr.lymar1@gmail.com>
License: MIT
License-File: LICENSE
Keywords: api,async,ecommerce,python,vinted,vinted-api,web-scraping
Classifier: Development Status :: 5 - Production/Stable
Classifier: Framework :: AsyncIO
Classifier: Intended Audience :: Developers
Classifier: Intended Audience :: Information Technology
Classifier: License :: OSI Approved :: MIT License
Classifier: Operating System :: OS Independent
Classifier: Programming Language :: Python :: 3
Classifier: Programming Language :: Python :: 3.10
Classifier: Programming Language :: Python :: 3.11
Classifier: Programming Language :: Python :: 3.12
Classifier: Programming Language :: Python :: 3.13
Classifier: Topic :: Communications
Classifier: Topic :: Internet :: WWW/HTTP
Classifier: Topic :: Software Development :: Libraries :: Python Modules
Classifier: Topic :: Utilities
Classifier: Typing :: Typed
Requires-Python: >=3.10
Requires-Dist: curl-cffi<0.13.0,>=0.12.0
